tc_localagent/agent_runner.py
tc_localagent/browser_context.py
tc_localagent/cli.py
tc_localagent/datas.py
tc_localagent/main.py
tc_localagent/server.py
tc_localagent-0.0.1.dist-info/METADATA
tc_localagent-0.0.1.dist-info/WHEEL
tc_localagent-0.0.1.dist-info/entry_points.txt
tc_localagent-0.0.1.dist-info/top_level.txt
tc_localagent-0.0.1.dist-info/RECORD
